flaskcord/__init__.py
flaskcord/_http.py
flaskcord/client.py
flaskcord/configs.py
flaskcord/exceptions.py
flaskcord/utils.py
flaskcord/models/__init__.py
flaskcord/models/base.py
flaskcord/models/connections.py
flaskcord/models/guild.py
flaskcord/models/integration.py
flaskcord/models/user.py
flaskcord/types/__init__.py
flaskcord/types/permissions.py
tests/__init__.py
tests/test_app.py
tests/test_factory_app.py
Flaskcord-0.1.70.dist-info/LICENSE
Flaskcord-0.1.70.dist-info/METADATA
Flaskcord-0.1.70.dist-info/WHEEL
Flaskcord-0.1.70.dist-info/top_level.txt
Flaskcord-0.1.70.dist-info/RECORD
